clodxy/__init__.py
clodxy/__main__.py
clodxy/cli.py
clodxy/config.py
clodxy/main.py
clodxy/py.typed
clodxy/translate.py
clodxy-0.2.3.dist-info/licenses/LICENSE
clodxy-0.2.3.dist-info/METADATA
clodxy-0.2.3.dist-info/WHEEL
clodxy-0.2.3.dist-info/entry_points.txt
clodxy-0.2.3.dist-info/top_level.txt
clodxy-0.2.3.dist-info/RECORD
