Metadata-Version: 2.4
Name: clodxy
Version: 0.2.3
Summary: Claude Code to OpenAI-compatible API proxy
License-Expression: Apache-2.0
Project-URL: Repository, https://github.com/lyssieth/clodxy
Keywords: api,proxy,claude,openai,llm,anthropic
Classifier: Development Status :: 3 - Alpha
Classifier: Environment :: Web Environment
Classifier: Intended Audience :: Developers
Classifier: Programming Language :: Python :: 3
Classifier: Programming Language :: Python :: 3.12
Classifier: Programming Language :: Python :: 3.13
Classifier: Programming Language :: Python :: 3.14
Classifier: Topic :: Utilities
Requires-Python: >=3.12
License-File: LICENSE
Requires-Dist: argcomplete>=3.6.3
Requires-Dist: dacite>=1.9.2
Requires-Dist: fastapi>=0.128.0
Requires-Dist: httpx>=0.28.1
Requires-Dist: uvicorn>=0.40.0
Dynamic: license-file
